redblackgraph-0.6.0.dist-info/WHEEL
redblackgraph-0.6.0.dist-info/entry_points.txt
redblackgraph-0.6.0.dist-info/METADATA
redblackgraph-0.6.0.dist-info/RECORD
redblackgraph/constants.py
redblackgraph/__init__.py
redblackgraph/types/transitive_closure.py
redblackgraph/types/color.py
redblackgraph/types/ordering.py
redblackgraph/types/__init__.py
redblackgraph/types/relationship.py
redblackgraph/reference/generation.py
redblackgraph/reference/shortest_path.py
redblackgraph/reference/topological_sort.py
redblackgraph/reference/calc_relationship.py
redblackgraph/reference/components.py
redblackgraph/reference/mat_avos.py
redblackgraph/reference/transitive_closure.py
redblackgraph/reference/vec_avos.py
redblackgraph/reference/permutation.py
redblackgraph/reference/ordering.py
redblackgraph/reference/relational_composition.py
redblackgraph/reference/__init__.py
redblackgraph/reference/rbg_math.py
redblackgraph/sparse/rbm.py
redblackgraph/sparse/_sparsetools.cpython-310-x86_64-linux-gnu.so
redblackgraph/sparse/avos.py
redblackgraph/sparse/generate_sparsetools.py
redblackgraph/sparse/__init__.py
redblackgraph/sparse/csgraph/_relational_composition.cpython-310-x86_64-linux-gnu.so
redblackgraph/sparse/csgraph/_shortest_path.cpython-310-x86_64-linux-gnu.so
redblackgraph/sparse/csgraph/_rbg_math.cpython-310-x86_64-linux-gnu.so
redblackgraph/sparse/csgraph/transitive_closure.py
redblackgraph/sparse/csgraph/cycleerror.py
redblackgraph/sparse/csgraph/_permutation.cpython-310-x86_64-linux-gnu.so
redblackgraph/sparse/csgraph/_validation.py
redblackgraph/sparse/csgraph/_tools.cpython-310-x86_64-linux-gnu.so
redblackgraph/sparse/csgraph/_ordering.cpython-310-x86_64-linux-gnu.so
redblackgraph/sparse/csgraph/__init__.py
redblackgraph/sparse/csgraph/_components.cpython-310-x86_64-linux-gnu.so
redblackgraph/core/avos.py
redblackgraph/core/redblack.py
redblackgraph/core/_redblackgraph.cpython-310-x86_64-linux-gnu.so
redblackgraph/core/__init__.py
redblackgraph/util/test_support.py
redblackgraph/util/capture.py
redblackgraph/util/graph_builder.py
redblackgraph/util/__init__.py
