Metadata-Version: 2.1
Name: redblackgraph
Version: 0.6.0
Summary: Red Black Graph - AVOS algebra for graph computation
Keywords: graph,algebra,AVOS,sparse,matrix
Author-Email: Daniel Rapp <rappdw@gmail.com>
Maintainer-Email: Daniel Rapp <rappdw@gmail.com>
License: AGPLv3+
Classifier: Development Status :: 5 - Production/Stable
Classifier: Intended Audience :: Developers
Classifier: Topic :: Scientific/Engineering :: Visualization
Classifier: Topic :: Software Development :: Version Control :: Git
Classifier: Topic :: Software Development :: Libraries :: Python Modules
Classifier: License :: OSI Approved :: GNU Affero General Public License v3 or later (AGPLv3+)
Classifier: Programming Language :: Python :: 3
Classifier: Programming Language :: Python :: 3.10
Classifier: Programming Language :: Python :: 3.11
Classifier: Programming Language :: Python :: 3.12
Classifier: Programming Language :: C
Classifier: Programming Language :: C++
Classifier: Programming Language :: Cython
Project-URL: Homepage, https://github.com/rappdw/redblackgraph
Project-URL: Repository, https://github.com/rappdw/redblackgraph
Project-URL: Download, https://github.com/rappdw/redblackgraph
Requires-Python: >=3.10
Requires-Dist: numpy<3.0,>=2.0.0
Requires-Dist: scipy>=1.11.0
Provides-Extra: io
Requires-Dist: fs-crawler>=0.3.2; extra == "io"
Requires-Dist: XlsxWriter; extra == "io"
Provides-Extra: dev
Requires-Dist: wheel>=0.29; extra == "dev"
Provides-Extra: test
Requires-Dist: pytest>=3.0; extra == "test"
Requires-Dist: pytest-cov>=2.4; extra == "test"
Requires-Dist: pylint>=1.8.1; extra == "test"
Requires-Dist: fs-crawler>=0.3.2; extra == "test"
Requires-Dist: XlsxWriter; extra == "test"
